odoo/addons/ssi_risk_limit/README.rst
odoo/addons/ssi_risk_limit/__init__.py
odoo/addons/ssi_risk_limit/__manifest__.py
odoo/addons/ssi_risk_limit/menu.xml
odoo/addons/ssi_risk_limit/approval_template/risk_limit_assignment.xml
odoo/addons/ssi_risk_limit/approval_template/risk_limit_batch_assignment.xml
odoo/addons/ssi_risk_limit/data/base_automation_data.xml
odoo/addons/ssi_risk_limit/data/ir_actions_server_data.xml
odoo/addons/ssi_risk_limit/demo/risk_limit_item.xml
odoo/addons/ssi_risk_limit/demo/risk_limit_type.xml
odoo/addons/ssi_risk_limit/i18n/ssi_risk_limit.pot
odoo/addons/ssi_risk_limit/ir_sequence/risk_limit_assignment.xml
odoo/addons/ssi_risk_limit/ir_sequence/risk_limit_batch_assignment.xml
odoo/addons/ssi_risk_limit/models/__init__.py
odoo/addons/ssi_risk_limit/models/partner_risk_limit.py
odoo/addons/ssi_risk_limit/models/res_partner.py
odoo/addons/ssi_risk_limit/models/res_partner_default_risk_limit_composite_detail.py
odoo/addons/ssi_risk_limit/models/res_partner_default_risk_limit_detail.py
odoo/addons/ssi_risk_limit/models/risk_limit_assignment.py
odoo/addons/ssi_risk_limit/models/risk_limit_assignment_composite_detail.py
odoo/addons/ssi_risk_limit/models/risk_limit_assignment_detail.py
odoo/addons/ssi_risk_limit/models/risk_limit_batch_assignment.py
odoo/addons/ssi_risk_limit/models/risk_limit_item.py
odoo/addons/ssi_risk_limit/models/risk_limit_type.py
odoo/addons/ssi_risk_limit/models/risk_limit_type_composite_item.py
odoo/addons/ssi_risk_limit/models/risk_limit_type_item.py
odoo/addons/ssi_risk_limit/policy_template/risk_limit_assignment.xml
odoo/addons/ssi_risk_limit/policy_template/risk_limit_batch_assignment.xml
odoo/addons/ssi_risk_limit/security/res_groups.xml
odoo/addons/ssi_risk_limit/security/ir_model_access/create_risk_limit_assignment.xml
odoo/addons/ssi_risk_limit/security/ir_model_access/partner_risk_limit.xml
odoo/addons/ssi_risk_limit/security/ir_model_access/risk_limit_assignment.xml
odoo14_addon_ssi_risk_limit-14.0.3.3.0.dist-info/METADATA
odoo14_addon_ssi_risk_limit-14.0.3.3.0.dist-info/WHEEL
odoo14_addon_ssi_risk_limit-14.0.3.3.0.dist-info/top_level.txt
odoo14_addon_ssi_risk_limit-14.0.3.3.0.dist-info/RECORD
